{
 "power_up_id": 66,
 "modulated_steps": [],
 "params": [
  {
   "param": 0,
   "coeff_steps": [
    105
   ],
   "delay_steps": [],
   "coeff_table": {
    "105": [
     -127,
     -127,
     -127,
     -127,
     -127,
     -115,
     -99,
     -87
    ]
   },
   "delay_table": {}
  },
  {
   "param": 1,
   "coeff_steps": [
    101,
    105,
    106,
    115
   ],
   "delay_steps": [],
   "coeff_table": {
    "101": [
     -40,
     -40,
     -40,
     -40,
     -40,
     -28,
     -12,
     -40
    ],
    "105": [
     -127,
     -127,
     -127,
     -127,
     -127,
     -115,
     -99,
     -87
    ],
    "106": [
     -40,
     -40,
     -40,
     -40,
     -40,
     -28,
     -12,
     -40
    ],
    "115": [
     -43,
     -43,
     -43,
     -43,
     -43,
     -31,
     -15,
     -43
    ]
   },
   "delay_table": {}
  },
  {
   "param": 2,
   "coeff_steps": [
    107,
    108
   ],
   "delay_steps": [],
   "coeff_table": {
    "107": [
     -15,
     -31,
     -47,
     -63,
     -79,
     -95,
     -111,
     -127
    ],
    "108": [
     -108,
     -92,
     -76,
     -60,
     -44,
     -28,
     -12,
     -124
    ]
   },
   "delay_table": {}
  },
  {
   "param": 3,
   "coeff_steps": [
    112,
    113
   ],
   "delay_steps": [],
   "coeff_table": {
    "112": [
     -87,
     -87,
     -87,
     -87,
     -87,
     -95,
     -111,
     -127
    ],
    "113": [
     -37,
     -37,
     -37,
     -37,
     -37,
     -29,
     -13,
     -125
    ]
   },
   "delay_table": {}
  },
  {
   "param": 4,
   "coeff_steps": [
    78,
    89
   ],
   "delay_steps": [],
   "coeff_table": {
    "78": [
     -59,
     -59,
     -67,
     -79,
     -91,
     -103,
     -107,
     -63
    ],
    "89": [
     -59,
     -59,
     -67,
     -79,
     -91,
     -103,
     -107,
     -63
    ]
   },
   "delay_table": {}
  },
  {
   "param": 5,
   "coeff_steps": [],
   "delay_steps": [
    117
   ],
   "coeff_table": {},
   "delay_table": {
    "117": [
     10941,
     9377,
     7201,
     3121,
     129,
     129,
     129,
     129
    ]
   }
  }
 ]
}